passwordless/__init__.py
passwordless/passwordless.py
passwordless_38-0.0.9.dist-info/METADATA
passwordless_38-0.0.9.dist-info/WHEEL
passwordless_38-0.0.9.dist-info/top_level.txt
passwordless_38-0.0.9.dist-info/RECORD
