Metadata-Version: 2.1
Name: passwordless-38
Version: 0.0.9
Summary: A client library for Bitwardens Passwordless.dev API
Author: Bitwarden
Author-email: hello@bitwarden.com
Classifier: Development Status :: 3 - Alpha
Classifier: Intended Audience :: Developers
Classifier: License :: OSI Approved :: MIT License
Classifier: Programming Language :: Python :: 3.8
Classifier: Programming Language :: Python :: 3.9
Requires-Dist: requests
